Workbook

Sheet 市集新手店主財務報表模板 V2
A1: 主報表：市集店主財務報表
A3: 【第一部分：損益表】
A4: 損益表項目 | B4: 金額 (元) | C4: 說明
A6: 銷貨 | B6: ='銷貨'!B32 -> 3865 | C6: 自下方「銷貨原始分錄明細表」自動連動加總
A7: 減：銷貨退回 | B7: 0 | C7: 顧客退貨或現場給予的特別折讓
A8: 銷貨淨額 | B8: =B6-B7 -> 3865 | C8: 銷貨收入總額 - 銷貨退回及折讓
A9: 減：銷貨成本
A10: 期初存貨 | B10: 0 | C10: 本次市集開始前的商品庫存總價值
A11: 加：購貨 | B11: ='購貨'!B29 -> 2720 | C11: 自下方「購貨原始分錄明細表」自動連動加總
A12: 減：期末存貨 | B12: ='購貨'!D41 -> 669.71409 | C12: 自下方「期末存貨盤點明細表」自動連動加總
A13: 銷貨成本總計 | B13: =B10+B11-B12 -> 2050.2859 | C13: 期初存貨 + 本期購貨 - 期末存貨
A14: 毛利 | B14: =B8-B13 -> 1814.7141 | C14: 營業收入淨額 - 銷貨成本總計
A15: 減：費用
A16: 攤位租金 | B16: 1500 | C16: 市集攤位基本固定租金
A17: 包材與日常雜項 | B17: 100 | C17: 紙袋、塑膠袋、攤位裝飾道具等支出
A18: 交通與運費 | B18: 200 | C18: 運送貨物或往返市集的交通開銷
A19: 行銷與推廣費 | B19: 500 | C19: 現場小贈品、線上宣傳廣告等
A20: 營業費用總計 | B20: =SUM(B16:B19) -> 2300 | C20: 各項擺攤營運費用加總
A21: 淨利 | B21: =B14-B20 -> -485.28591 | C21: 銷貨毛利 - 營業費用總計
A23: 【第二部分：關鍵財務比率與資本項目】
A24: 會計項目/比率名稱 | B24: 數值 / 結果 | C24: 比率計算說明
A25: 業主投入資本 | B25: 5000 | C25: 「本次擺攤準備的總本金」（如：備用零錢、初期材料、硬體設備基金）
A26: 毛利率 | B26: =B14/B8 -> 0.46952499 | C26: 銷貨毛利 ÷ 營業收入淨額（代表產品的核心獲利能力）
A27: 淨利率 | B27: =B21/B8 -> -0.1255591 | C27: 營業淨利 ÷ 營業收入淨額（代表最終扣除所有成本費用的實賺比率）
A28: 資本回報率 (ROI) | B28: =B21/B25 -> -0.097057182 | C28: 營業淨利 ÷ 業主投入資本（代表你投入的每一元本金幫你賺回多少利潤）
A30: 【第三部分：銷貨原始分錄明細表 (Sales Log)】
A31: 交易日期 | B31: 銷貨金額 (元) | C31: 數量 | D31: 備註
A32: 46143 | B32: 500 | C32: 5
A33: 46143 | B33: 1200 | C33: 3
A52: 【第四部分：購貨原始分錄明細表 (Purchases Log)】
A53: 交易日期 | B53: 購貨金額 (元) | C53: 數量 | D53: 備註
A54: 46137 | B54: 3000 | C54: 100 | D54: 範例：進貨原料明細
A55: 46138 | B55: 1000 | C55: 20 | D55: 範例：進貨成品明細
A74: 【第五部分：期末存貨盤點明細表 (Ending Inventory)】
A75: 產品名稱 | B75: 剩餘數量 | C75: 期末存貨總價值 (元) | D75: 說明
A76: 商品A | B76: 10 | C76: =B76*#REF! -> #REF! | D76: 數量乘以單位成本
A77: 商品B | B77: 5 | C77: =B77*#REF! -> #REF! | D77: 數量乘以單位成本
A95: 總計： | C95: =SUM(C76:C94) -> #REF! | D95: 自動計算所有剩餘存貨的總價值並向上連動至銷貨成本

Sheet 購貨
A1: 【第四部分：購貨原始分錄明細表 (Purchases Log)】
A2: 品項 | B2: 產品單價($) | C2: 貨品總數
A3: 商品A | B3: =SUMIF($C$7:$C$23,A3,$B$7:$B$23)/ SUMIF($C$7:$C$23,A3,$D$7:$D$23) -> 13.451327 | C3: =SUMIF($C$7:$C$23,A3,$D$7:$D$23) -> 113
A4: 商品B | B4: =SUMIF($C$7:$C$23,A4,$B$7:$B$23)/SUMIF($C$7:$C$23,A4,$D$7:$D$23) -> 13.846154 | C4: =SUMIF($C$7:$C$23,A4,$D$7:$D$23) -> 65
A5: 商品C | B5: =SUMIF($C$7:$C$23,A5,$B$7:$B$23)/SUMIF($C$7:$C$23,A5,$D$7:$D$23) -> 30 | C5: =SUMIF($C$7:$C$23,A5,$D$7:$D$23) -> 10
A6: 交易日期 | B6: 購貨金額 (元) | C6: 品項 | D6: 數量 | E6: 備註/單據編號
A7: 46137 | B7: 1000 | C7: 商品A | D7: 100 | E7: P001
A8: 46138 | B8: 700 | C8: 商品B | D8: 20
A9: 46139 | B9: 520 | C9: 商品A | D9: 13
A10: 46140 | B10: 300 | C10: 商品C | D10: 10
A11: 46141 | B11: 100 | C11: 商品B | D11: 25
A12: 46142 | B12: 100 | C12: 商品B | D12: 20
A13: 46143 | C13: 商品B
A14: 46144
A15: 46145
A16: 46146
A17: 46147
A18: 46148
A19: 46149
A20: 46150
A21: 46151
A22: 46152
A23: 46152
A29: 購貨總額 | B29: =sum(B3*C3+B4*C4+B5*C5) -> 2720
A36: 【第五部分：期末存貨盤點明細表 (Ending Inventory)】
A37: 產品名稱 | B37: 剩餘數量 | C37: 單位成本 (元) | D37: 期末存貨總價值 (元)
A38: 商品A | B38: =C3-'銷貨'!C3 -> 28 | C38: =B3 -> 13.451327 | D38: =B38*C38 -> 376.63717
A39: 商品B | B39: =C4-'銷貨'!C4 -> 32 | C39: =B4 -> 13.846154 | D39: =B39*C39 -> 443.07692
A40: 商品C | B40: =C5-'銷貨'!C5 -> -5 | C40: =B5 -> 30 | D40: =B40*C40 -> -150
A41: 期末存貨總額 | D41: =sum(D38:D40) -> 669.71409
A57: 總計： | D57: =SUM(D38:D56) -> 1339.4282 | E57: 自動計算所有剩餘存貨的總價值並向上連動至銷貨成本

Sheet 銷貨
A1: 【第三部分：銷貨原始分錄明細表 (Sales Log)】
A2: 品項 | B2: 產品單價($) | C2: 銷貨總數
A3: 商品A | B3: 25 | C3: =SUMIF($C$7:$C$23,A3,$D$7:$D$23) -> 85
A4: 商品B | B4: 30 | C4: =SUMIF($C$7:$C$23,A4,$D$7:$D$23) -> 33
A5: 商品C | B5: 50 | C5: =SUMIF($C$7:$C$23,A5,$D$7:$D$23) -> 15
A6: 交易日期 | B6: 銷貨金額 (元) | C6: 產品名稱 | D6: 數量 | E6: 備註/交易編號
A7: 46143 | B7: =iferror(VLOOKUP(C7,$A$3:$B$5,2,false)*D7,"") -> 150 | C7: 商品B | D7: 5 | E7: V001
A8: 46143 | B8: =iferror(VLOOKUP(C8,$A$3:$B$5,2,false)*D8,"") -> 250 | C8: 商品A | D8: 10 | E8: V002
A9: 46144 | B9: =iferror(VLOOKUP(C9,$A$3:$B$5,2,false)*D9,"") -> 180 | C9: 商品B | D9: 6 | E9: V002
A10: 46145 | B10: =iferror(VLOOKUP(C10,$A$3:$B$5,2,false)*D10,"") -> 210 | C10: 商品B | D10: 7
A11: 46146 | B11: =iferror(VLOOKUP(C11,$A$3:$B$5,2,false)*D11,"") -> 750 | C11: 商品C | D11: 15
A12: 46147 | B12: =iferror(VLOOKUP(C12,$A$3:$B$5,2,false)*D12,"") -> 375 | C12: 商品A | D12: 15
A13: 46148 | B13: =iferror(VLOOKUP(C13,$A$3:$B$5,2,false)*D13,"") -> 450 | C13: 商品B | D13: 15
A14: 46149 | B14: =iferror(VLOOKUP(C14,$A$3:$B$5,2,false)*D14,"") -> 1500 | C14: 商品A | D14: 60
A15: 46150 | B15: =iferror(VLOOKUP(C15,$A$3:$B$5,2,false)*D15,"")
A16: 46151 | B16: =iferror(VLOOKUP(C16,$A$3:$B$5,2,false)*D16,"")
A17: 46152 | B17: =iferror(VLOOKUP(C17,$A$3:$B$5,2,false)*D17,"")
A18: 46153 | B18: =iferror(VLOOKUP(C18,$A$3:$B$5,2,false)*D18,"")
A19: 46154 | B19: =iferror(VLOOKUP(C19,$A$3:$B$5,2,false)*D19,"")
A20: 46155 | B20: =iferror(VLOOKUP(C20,$A$3:$B$5,2,false)*D20,"")
B21: =iferror(VLOOKUP(C21,$A$3:$B$5,2,false)*D21,"")
B22: =iferror(VLOOKUP(C22,$A$3:$B$5,2,false)*D22,"")
B23: =iferror(VLOOKUP(C23,$A$3:$B$5,2,false)*D23,"")
B24: =iferror(VLOOKUP(C24,$A$3:$B$5,2,false)*D24,"")
B25: =iferror(VLOOKUP(C25,$A$3:$B$5,2,false)*D25,"")
B26: =iferror(VLOOKUP(C26,$A$3:$B$5,2,false)*D26,"")
B27: =iferror(VLOOKUP(C27,$A$3:$B$5,2,false)*D27,"")
B28: =iferror(VLOOKUP(C28,$A$3:$B$5,2,false)*D28,"")
B29: =iferror(VLOOKUP(C29,$A$3:$B$5,2,false)*D29,"")
B30: =iferror(VLOOKUP(C30,$A$3:$B$5,2,false)*D30,"")
B31: =iferror(VLOOKUP(C31,$A$3:$B$5,2,false)*D31,"")
A32: 銷貨總額 | B32: =sum(B7:B31) -> 3865
